{"Q174193":"United Kingdom of Great Britain and Ireland","Q161885":"Kingdom of Great Britain","Q145":"United Kingdom","Q179876":"Kingdom of England","Q769":"Grenada","Q711":"Mongolia","Q265":"Uzbekistan","Q38":"Italy","Q869":"Thailand","Q224":"Croatia","Q27":"Ireland","Q833":"Malaysia","Q796":"Iraq","Q754":"Trinidad and Tobago","Q1246":"Kosovo","Q232":"Kazakhstan","Q846":"Qatar","Q43":"Turkey","Q1036":"Uganda","Q148":"People's Republic of China","Q794":"Iran","Q878":"United Arab Emirates","Q928":"Philippines","Q215530":"Kingdom of Ireland","Q844250":"Lordship of Ireland","Q105313":"Kingdom of Wessex","Q230791":"Kingdom of Scotland","Q105092":"Kingdom of Mercia","Q2277":"Roman Empire","Q110888":"Kingdom of Essex"}